HISTORY.rst
LICENSE
MANIFEST.in
README.rst
setup.cfg
setup.py
bin/1pwd
onepyssword/__init__.py
onepyssword/app.py
onepyssword/logic.py
onepyssword/py3k.py
onepyssword.egg-info/PKG-INFO
onepyssword.egg-info/SOURCES.txt
onepyssword.egg-info/dependency_links.txt
onepyssword.egg-info/not-zip-safe
onepyssword.egg-info/requires.txt
onepyssword.egg-info/top_level.txt