Metadata-Version: 1.1
Name: onepyssword
Version: 0.3.2
Summary: A command line interface for 1Password
Home-page: http://gr1n.github.io/1pwd/
Author: Nikita Grishko
Author-email: grin.minsk@gmail.com
License: MIT
Platform: UNKNOWN
Classifier: License :: OSI Approved :: MIT License
Classifier: Programming Language :: Python
Classifier: Programming Language :: Python :: 2
Classifier: Programming Language :: Python :: 2.7
Classifier: Programming Language :: Python :: 3
Classifier: Programming Language :: Python :: 3.3
Classifier: Programming Language :: Python :: Implementation :: CPython
